{"name":"Weepinbell","type1":"Grass","type2":"Poison","hp":65,"attack":90,"defense":50,"spAttack":85,"spDefense":45,"speed":55,"learnset":[{"level":1,"move":"Vine Whip","type":"Grass","power":45,"pp":25},{"level":1,"move":"Wrap","type":"Normal","power":15,"pp":20},{"level":13,"move":"Sleep Powder","type":"Grass","power":0,"pp":15},{"level":15,"move":"Poison Powder","type":"Poison","power":0,"pp":35},{"level":23,"move":"Acid","type":"Poison","power":40,"pp":30},{"level":27,"move":"Knock Off","type":"Dark","power":65,"pp":20},{"level":39,"move":"Razor Leaf","type":"Grass","power":55,"pp":25},{"level":41,"move":"Slam","type":"Normal","power":80,"pp":20},{"level":47,"move":"Poison Jab","type":"Poison","power":80,"pp":20}]}