{"name":"Dugtrio","type1":"Ground","hp":35,"attack":100,"defense":50,"spAttack":50,"spDefense":70,"speed":120,"learnset":[{"level":0,"move":"Sand Tomb","type":"Ground","power":35,"pp":15},{"level":1,"move":"Astonish","type":"Ghost","power":30,"pp":15},{"level":1,"move":"Growl","type":"Normal","power":0,"pp":40},{"level":1,"move":"Night Slash","type":"Dark","power":70,"pp":15},{"level":1,"move":"Sand Attack","type":"Ground","power":0,"pp":15},{"level":1,"move":"Scratch","type":"Normal","power":40,"pp":35},{"level":1,"move":"Tri Attack","type":"Normal","power":80,"pp":10},{"level":10,"move":"Mud-Slap","type":"Ground","power":20,"pp":10},{"level":16,"move":"Bulldoze","type":"Ground","power":60,"pp":20},{"level":17,"move":"Dig","type":"Ground","power":80,"pp":10},{"level":20,"move":"Sucker Punch","type":"Dark","power":70,"pp":5},{"level":21,"move":"Fury Swipes","type":"Normal","power":18,"pp":15},{"level":24,"move":"Slash","type":"Normal","power":70,"pp":20},{"level":25,"move":"Mud Bomb","type":"Ground","power":65,"pp":10},{"level":28,"move":"Earth Power","type":"Ground","power":90,"pp":10},{"level":45,"move":"Earthquake","type":"Ground","power":100,"pp":10}]}